cut_video/__init__.py
cut_video/cut_video.py
cut_video-0.0.10.data/data/cut_video/to_erase.json
cut_video-0.0.10.data/scripts/cut_video.py
cut_video-0.0.10.dist-info/LICENCE
cut_video-0.0.10.dist-info/METADATA
cut_video-0.0.10.dist-info/WHEEL
cut_video-0.0.10.dist-info/entry_points.txt
cut_video-0.0.10.dist-info/top_level.txt
cut_video-0.0.10.dist-info/RECORD
